spatialdata_xenium_explorer/__init__.py
spatialdata_xenium_explorer/_constants.py
spatialdata_xenium_explorer/_logging.py
spatialdata_xenium_explorer/cli/app.py
spatialdata_xenium_explorer/converter.py
spatialdata_xenium_explorer/core/__init__.py
spatialdata_xenium_explorer/core/images.py
spatialdata_xenium_explorer/core/points.py
spatialdata_xenium_explorer/core/shapes.py
spatialdata_xenium_explorer/core/table.py
spatialdata_xenium_explorer/main.py
spatialdata_xenium_explorer/utils.py
spatialdata_xenium_explorer-0.1.7.dist-info/LICENSE
spatialdata_xenium_explorer-0.1.7.dist-info/METADATA
spatialdata_xenium_explorer-0.1.7.dist-info/WHEEL
spatialdata_xenium_explorer-0.1.7.dist-info/entry_points.txt
spatialdata_xenium_explorer-0.1.7.dist-info/RECORD
