Metadata-Version: 2.1
Name: spatialdata_xenium_explorer
Version: 0.1.7
Summary: Converting any SpatialData object into files that can be open by the Xenium Explorer
Home-page: https://quentinblampey.github.io/spatialdata_xenium_explorer/
License: BSD-3-Clause
Author: Quentin Blampey
Author-email: quentin.blampey@gmail.com
Requires-Python: >=3.9,<3.11
Classifier: License :: OSI Approved :: BSD License
Classifier: Operating System :: MacOS :: MacOS X
Classifier: Operating System :: Microsoft :: Windows
Classifier: Operating System :: POSIX :: Linux
Classifier: Programming Language :: Python :: 3
Classifier: Programming Language :: Python :: 3.9
Classifier: Programming Language :: Python :: 3.10
Classifier: Topic :: Scientific/Engineering
Requires-Dist: botocore (==1.34.19)
Requires-Dist: spatialdata (>=0.1.2)
Requires-Dist: typer (>=0.9.0)
Project-URL: Documentation, https://quentinblampey.github.io/spatialdata_xenium_explorer/
Project-URL: Repository, https://github.com/quentinblampey/spatialdata_xenium_explorer
